Workbook

Sheet TB_Salarios_Func
A1: Funcionário | B1: Salário mensal | C1: Vale-Transporte | D1: Total Mensal | E1: INSS | F1: FGTS | G1: 13o Salário | H1: Férias | I1: Total
A2: João | B2: 2308 | C2: 316.82 | D2: 2624.82 | E2: 461.6 | F2: 184.64 | G2: 192.33333 | H2: 256.44444 | I2: 3719.8378
A3: Marta | B3: 2968.94 | C3: 318.94 | D3: 3287.88 | E3: 593.788 | F3: 237.5152 | G3: 247.41167 | H3: 329.88222 | I3: 4696.4771
A4: Ana | B4: 3108.7 | C4: 318.94 | D4: 3427.64 | E4: 621.74 | F4: 248.696 | G4: 259.05833 | H4: 345.41111 | I4: 4902.5454

Sheet Extrato
A1: Data | B1: Descrição | C1: Valor (R$) | D1: Saldo (R$) | E1: Nome do Mês | F1: Categoria de Gasto
A2: 45294 | B2: PAG TIT IMOB | C2: -2000 | D2: 28000 | E2: janeiro | F2: Gasto Café
A3: 45296 | B3: PIX LUZ | C3: -150 | D3: 27850 | E3: janeiro | F3: Pessoal
A4: 45296 | B4: PIX ÁGUA | C4: -85 | D4: 27765 | E4: janeiro | F4: Pessoal
A5: 45299 | B5: RSHOP FORNECEDOR | C5: -700 | D5: 27065 | E5: janeiro | F5: Gasto Café
A6: 45301 | B6: RSHOP SUPERMERCADO | C6: -180 | D6: 26885 | E6: janeiro | F6: Gasto Café
A7: 45301 | B7: SISPAG TON | C7: 10163.75 | D7: 37048.75 | E7: janeiro | F7: Recebimento
A8: 45303 | B8: PAG TIT INTERNET | C8: -180 | D8: 36868.75 | E8: janeiro | F8: Gasto Café
A9: 45303 | B9: PIX INTERNET | C9: -99.9 | D9: 36768.85 | E9: janeiro | F9: Pessoal
A10: 45306 | B10: PAG TRANSF JOAO | C10: -2624.82 | D10: 34144.03 | E10: janeiro | F10: Funcionários
A11: 45306 | B11: PAG TRANSF MARTA | C11: -3287.88 | D11: 30856.15 | E11: janeiro | F11: Funcionários
A12: 45306 | B12: PAG TRANSF ANA | C12: -3427.64 | D12: 27428.51 | E12: janeiro | F12: Funcionários
A13: 45311 | B13: TEF CONTABILIDADE | C13: -2847.98 | D13: 24580.53 | E13: janeiro | F13: Contabilidade
... A136: 45514 | B136: SISPAG TON | C136: 9800 | D136: 55000.36 | E136: agosto | F136: Recebimento

Sheet Custo Funcionários
A1: Valores Mensais por Funcionário | H1: Salário Mensal | I1: Dif Contabilidade | J1: Gasto Café | K1: Provisão | L1: Produtividade por Funcionário
A2: Funcionário | B2: Salário Mensal | C2: Encargos | D2: Provisão (Férias + 13o) | E2: Diferença Mensal | G2: janeiro | H2: =SUMIFS(Extrato[Valor (R$)],Extrato[Descrição],"PAG TRANSF*",Extrato[Nome do Mês],G2)*-1 -> 9340.34 | I2: =SUMIFS(Extrato[Valor (R$)],Extrato[Descrição],"*CONTABILIDADE*",Extrato[Nome do Mês],G2)*-1 -> 2847.98 | J2: =SUMIFS(Extrato[Valor (R$)],Extrato[Categoria de Gasto],$J$1,Extrato[Nome do Mês],G2)*-1 -> 4610 | K2: 0 | L2: =IFERROR(GETPIVOTDATA("Total ",'Dinâmica Produt por Func'!$A$3,"Mês",LEFT(G2,3)),0) -> 20327.51
A3: João | B3: =TB_Salarios_Func!D2 -> 2624.82 | C3: =SUM(TB_Salarios_Func!E2:F2) -> 646.24 | D3: =SUM(TB_Salarios_Func!G2:H2) -> 448.77778 | E3: =SUM(C3:D3) -> 1095.0178 | G3: fevereiro | H3: =SUMIFS(Extrato[Valor (R$)],Extrato[Descrição],"PAG TRANSF*",Extrato[Nome do Mês],G3)*-1 -> 9340.34 | I3: =SUMIFS(Extrato[Valor (R$)],Extrato[Descrição],"*CONTABILIDADE*",Extrato[Nome do Mês],G3)*-1 -> 2847.98 | J3: =SUMIFS(Extrato[Valor (R$)],Extrato[Categoria de Gasto],$J$1,Extrato[Nome do Mês],G3)*-1 -> 4680 | K3: 0 | L3: =IFERROR(GETPIVOTDATA("Total ",'Dinâmica Produt por Func'!$A$3,"Mês",LEFT(G3,3)),0) -> 20671
A4: Marta | B4: =TB_Salarios_Func!D3 -> 3287.88 | C4: =SUM(TB_Salarios_Func!E3:F3) -> 831.3032 | D4: =SUM(TB_Salarios_Func!G3:H3) -> 577.29389 | E4: =SUM(C4:D4) -> 1408.5971 | G4: março | H4: =SUMIFS(Extrato[Valor (R$)],Extrato[Descrição],"PAG TRANSF*",Extrato[Nome do Mês],G4)*-1 -> 9340.34 | I4: =SUMIFS(Extrato[Valor (R$)],Extrato[Descrição],"*CONTABILIDADE*",Extrato[Nome do Mês],G4)*-1 -> 2847.98 | J4: =SUMIFS(Extrato[Valor (R$)],Extrato[Categoria de Gasto],$J$1,Extrato[Nome do Mês],G4)*-1 -> 4710 | K4: 0 | L4: =IFERROR(GETPIVOTDATA("Total ",'Dinâmica Produt por Func'!$A$3,"Mês",LEFT(G4,3)),0) -> 20985.01
A5: Ana | B5: =TB_Salarios_Func!D4 -> 3427.64 | C5: =SUM(TB_Salarios_Func!E4:F4) -> 870.436 | D5: =SUM(TB_Salarios_Func!G4:H4) -> 604.46944 | E5: =SUM(C5:D5) -> 1474.9054 | G5: abril | H5: =SUMIFS(Extrato[Valor (R$)],Extrato[Descrição],"PAG TRANSF*",Extrato[Nome do Mês],G5)*-1 -> 9340.34 | I5: =SUMIFS(Extrato[Valor (R$)],Extrato[Descrição],"*CONTABILIDADE*",Extrato[Nome do Mês],G5)*-1 -> 2847.98 | J5: =SUMIFS(Extrato[Valor (R$)],Extrato[Categoria de Gasto],$J$1,Extrato[Nome do Mês],G5)*-1 -> 4410 | K5: 0 | L5: =IFERROR(GETPIVOTDATA("Total ",'Dinâmica Produt por Func'!$A$3,"Mês",LEFT(G5,3)),0) -> 21150
A6: Total | B6: =SUM(B3:B5) -> 9340.34 | C6: =SUM(C3:C5) -> 2347.9792 | D6: =SUM(D3:D5) -> 1630.5411 | E6: =SUM(E3:E5) -> 3978.5203 | G6: maio | H6: =SUMIFS(Extrato[Valor (R$)],Extrato[Descrição],"PAG TRANSF*",Extrato[Nome do Mês],G6)*-1 -> 9340.34 | I6: =SUMIFS(Extrato[Valor (R$)],Extrato[Descrição],"*CONTABILIDADE*",Extrato[Nome do Mês],G6)*-1 -> 2847.98 | J6: =SUMIFS(Extrato[Valor (R$)],Extrato[Categoria de Gasto],$J$1,Extrato[Nome do Mês],G6)*-1 -> 4630 | K6: 0 | L6: =IFERROR(GETPIVOTDATA("Total ",'Dinâmica Produt por Func'!$A$3,"Mês",LEFT(G6,3)),0) -> 21800
G7: junho | H7: =SUMIFS(Extrato[Valor (R$)],Extrato[Descrição],"PAG TRANSF*",Extrato[Nome do Mês],G7)*-1 -> 9340.34 | I7: =SUMIFS(Extrato[Valor (R$)],Extrato[Descrição],"*CONTABILIDADE*",Extrato[Nome do Mês],G7)*-1 -> 2847.98 | J7: =SUMIFS(Extrato[Valor (R$)],Extrato[Categoria de Gasto],$J$1,Extrato[Nome do Mês],G7)*-1 -> 4730 | K7: 0 | L7: =IFERROR(GETPIVOTDATA("Total ",'Dinâmica Produt por Func'!$A$3,"Mês",LEFT(G7,3)),0) -> 22100
G8: julho | H8: =SUMIFS(Extrato[Valor (R$)],Extrato[Descrição],"PAG TRANSF*",Extrato[Nome do Mês],G8)*-1 -> 9340.34 | I8: =SUMIFS(Extrato[Valor (R$)],Extrato[Descrição],"*CONTABILIDADE*",Extrato[Nome do Mês],G8)*-1 -> 2847.98 | J8: =SUMIFS(Extrato[Valor (R$)],Extrato[Categoria de Gasto],$J$1,Extrato[Nome do Mês],G8)*-1 -> 5395 | K8: 0 | L8: =IFERROR(GETPIVOTDATA("Total ",'Dinâmica Produt por Func'!$A$3,"Mês",LEFT(G8,3)),0) -> 22500
G9: agosto | H9: =SUMIFS(Extrato[Valor (R$)],Extrato[Descrição],"PAG TRANSF*",Extrato[Nome do Mês],G9)*-1 -> 0 | I9: =SUMIFS(Extrato[Valor (R$)],Extrato[Descrição],"*CONTABILIDADE*",Extrato[Nome do Mês],G9)*-1 -> 0 | J9: =SUMIFS(Extrato[Valor (R$)],Extrato[Categoria de Gasto],$J$1,Extrato[Nome do Mês],G9)*-1 -> 3300 | K9: 0 | L9: =IFERROR(GETPIVOTDATA("Total ",'Dinâmica Produt por Func'!$A$3,"Mês",LEFT(G9,3)),0) -> 0
G10: setembro | H10: =SUMIFS(Extrato[Valor (R$)],Extrato[Descrição],"PAG TRANSF*",Extrato[Nome do Mês],G10)*-1 -> 0 | I10: =SUMIFS(Extrato[Valor (R$)],Extrato[Descrição],"*CONTABILIDADE*",Extrato[Nome do Mês],G10)*-1 -> 0 | J10: =SUMIFS(Extrato[Valor (R$)],Extrato[Categoria de Gasto],$J$1,Extrato[Nome do Mês],G10)*-1 -> 0 | K10: 0 | L10: =IFERROR(GETPIVOTDATA("Total ",'Dinâmica Produt por Func'!$A$3,"Mês",LEFT(G10,3)),0) -> 0
G11: outubro | H11: =SUMIFS(Extrato[Valor (R$)],Extrato[Descrição],"PAG TRANSF*",Extrato[Nome do Mês],G11)*-1 -> 0 | I11: =SUMIFS(Extrato[Valor (R$)],Extrato[Descrição],"*CONTABILIDADE*",Extrato[Nome do Mês],G11)*-1 -> 0 | J11: =SUMIFS(Extrato[Valor (R$)],Extrato[Categoria de Gasto],$J$1,Extrato[Nome do Mês],G11)*-1 -> 0 | K11: 0 | L11: =IFERROR(GETPIVOTDATA("Total ",'Dinâmica Produt por Func'!$A$3,"Mês",LEFT(G11,3)),0) -> 0
G12: novembro | H12: =SUMIFS(Extrato[Valor (R$)],Extrato[Descrição],"PAG TRANSF*",Extrato[Nome do Mês],G12)*-1 -> 0 | I12: =SUMIFS(Extrato[Valor (R$)],Extrato[Descrição],"*CONTABILIDADE*",Extrato[Nome do Mês],G12)*-1 -> 0 | J12: =SUMIFS(Extrato[Valor (R$)],Extrato[Categoria de Gasto],$J$1,Extrato[Nome do Mês],G12)*-1 -> 0 | K12: =SUM(TB_Salarios_Func[[13o Salário]:[Férias]])*12/2 -> 9783.2467 | L12: =IFERROR(GETPIVOTDATA("Total ",'Dinâmica Produt por Func'!$A$3,"Mês",LEFT(G12,3)),0) -> 0
G13: dezembro | H13: =SUMIFS(Extrato[Valor (R$)],Extrato[Descrição],"PAG TRANSF*",Extrato[Nome do Mês],G13)*-1 -> 0 | I13: =SUMIFS(Extrato[Valor (R$)],Extrato[Descrição],"*CONTABILIDADE*",Extrato[Nome do Mês],G13)*-1 -> 0 | J13: =SUMIFS(Extrato[Valor (R$)],Extrato[Categoria de Gasto],$J$1,Extrato[Nome do Mês],G13)*-1 -> 0 | K13: =SUM(TB_Salarios_Func[[13o Salário]:[Férias]])*12/2 -> 9783.2467 | L13: =IFERROR(GETPIVOTDATA("Total ",'Dinâmica Produt por Func'!$A$3,"Mês",LEFT(G13,3)),0) -> 0

Sheet Produtividade Funcionários
A1: Mês | B1: Funcionário | C1: Qtde de Vendas | D1: Total
A2: Jan | B2: João | C2: 90 | D2: 7525.67
A3: Jan | B3: Marta | C3: 120 | D3: 6025.67
A4: Jan | B4: Ana | C4: 60 | D4: 6776.17
A5: Fev | B5: João | C5: 95 | D5: 6314
A6: Fev | B6: Marta | C6: 125 | D6: 6845
A7: Fev | B7: Ana | C7: 65 | D7: 7512
A8: Mar | B8: João | C8: 100 | D8: 6528.34
A9: Mar | B9: Marta | C9: 130 | D9: 7528.33
A10: Mar | B10: Ana | C10: 70 | D10: 6928.34
A11: Abr | B11: João | C11: 135 | D11: 7350.01
A12: Abr | B12: Marta | C12: 75 | D12: 6949.99
A13: Abr | B13: Ana | C13: 85 | D13: 6850
... A25: Ago | B25: Ana | C25: 95 | D25: 3337.71

Sheet Dinâmica Produt por Func
A3: Rótulos de Linha | B3: Soma de Total
A4: Jan | B4: 20327.51
A5: Fev | B5: 20671
A6: Mar | B6: 20985.01
A7: Abr | B7: 21150
A8: Mai | B8: 21800
A9: Jun | B9: 22100
A10: Jul | B10: 22500
A11: Total Geral | B11: 149533.52

Sheet PF vs PJ
B1: Janeiro | C1: Fevereiro | D1: Março | E1: Abril | F1: Maio | G1: Junho | H1: Julho | I1: Agosto | J1: Setembro | K1: Outubro | L1: Novembro | M1: Dezembro
A2: Gasto Café | B2: =SUMIFS(Extrato[Valor (R$)], Extrato[Categoria de Gasto],$A2,Extrato[Nome do Mês],B$1)*-1 -> 4610 | C2: =SUMIFS(Extrato[Valor (R$)], Extrato[Categoria de Gasto],$A2,Extrato[Nome do Mês],C$1)*-1 -> 4680 | D2: =SUMIFS(Extrato[Valor (R$)], Extrato[Categoria de Gasto],$A2,Extrato[Nome do Mês],D$1)*-1 -> 4710 | E2: =SUMIFS(Extrato[Valor (R$)], Extrato[Categoria de Gasto],$A2,Extrato[Nome do Mês],E$1)*-1 -> 4410 | F2: =SUMIFS(Extrato[Valor (R$)], Extrato[Categoria de Gasto],$A2,Extrato[Nome do Mês],F$1)*-1 -> 4630 | G2: =SUMIFS(Extrato[Valor (R$)], Extrato[Categoria de Gasto],$A2,Extrato[Nome do Mês],G$1)*-1 -> 4730 | H2: =SUMIFS(Extrato[Valor (R$)], Extrato[Categoria de Gasto],$A2,Extrato[Nome do Mês],H$1)*-1 -> 5395 | I2: =SUMIFS(Extrato[Valor (R$)], Extrato[Categoria de Gasto],$A2,Extrato[Nome do Mês],I$1)*-1 -> 3300 | ... M2: =SUMIFS(Extrato[Valor (R$)], Extrato[Categoria de Gasto],$A2,Extrato[Nome do Mês],M$1)*-1 -> 0
A3: Pessoal | B3: =SUMIFS(Extrato[Valor (R$)], Extrato[Categoria de Gasto],$A3,Extrato[Nome do Mês],B$1)*-1 -> 1684.9 | C3: =SUMIFS(Extrato[Valor (R$)], Extrato[Categoria de Gasto],$A3,Extrato[Nome do Mês],C$1)*-1 -> 1599.9 | D3: =SUMIFS(Extrato[Valor (R$)], Extrato[Categoria de Gasto],$A3,Extrato[Nome do Mês],D$1)*-1 -> 1816.4 | E3: =SUMIFS(Extrato[Valor (R$)], Extrato[Categoria de Gasto],$A3,Extrato[Nome do Mês],E$1)*-1 -> 1905.1 | F3: =SUMIFS(Extrato[Valor (R$)], Extrato[Categoria de Gasto],$A3,Extrato[Nome do Mês],F$1)*-1 -> 1585.65 | G3: =SUMIFS(Extrato[Valor (R$)], Extrato[Categoria de Gasto],$A3,Extrato[Nome do Mês],G$1)*-1 -> 2173.05 | H3: =SUMIFS(Extrato[Valor (R$)], Extrato[Categoria de Gasto],$A3,Extrato[Nome do Mês],H$1)*-1 -> 1784.9 | I3: =SUMIFS(Extrato[Valor (R$)], Extrato[Categoria de Gasto],$A3,Extrato[Nome do Mês],I$1)*-1 -> 0 | ... M3: =SUMIFS(Extrato[Valor (R$)], Extrato[Categoria de Gasto],$A3,Extrato[Nome do Mês],M$1)*-1 -> 0
A4: Funcionários | B4: =SUMIFS(Extrato[Valor (R$)],Extrato[Categoria de Gasto],$A4,Extrato[Nome do Mês],B$1)*-1 -> 9340.34 | C4: =SUMIFS(Extrato[Valor (R$)],Extrato[Categoria de Gasto],$A4,Extrato[Nome do Mês],C$1)*-1 -> 9340.34 | D4: =SUMIFS(Extrato[Valor (R$)],Extrato[Categoria de Gasto],$A4,Extrato[Nome do Mês],D$1)*-1 -> 9340.34 | E4: =SUMIFS(Extrato[Valor (R$)],Extrato[Categoria de Gasto],$A4,Extrato[Nome do Mês],E$1)*-1 -> 9340.34 | F4: =SUMIFS(Extrato[Valor (R$)],Extrato[Categoria de Gasto],$A4,Extrato[Nome do Mês],F$1)*-1 -> 9340.34 | G4: =SUMIFS(Extrato[Valor (R$)],Extrato[Categoria de Gasto],$A4,Extrato[Nome do Mês],G$1)*-1 -> 9340.34 | H4: =SUMIFS(Extrato[Valor (R$)],Extrato[Categoria de Gasto],$A4,Extrato[Nome do Mês],H$1)*-1 -> 9340.34 | I4: =SUMIFS(Extrato[Valor (R$)],Extrato[Categoria de Gasto],$A4,Extrato[Nome do Mês],I$1)*-1 -> 0 | ... M4: =SUMIFS(Extrato[Valor (R$)],Extrato[Categoria de Gasto],$A4,Extrato[Nome do Mês],M$1)*-1 -> 0
A5: Contabilidade | B5: =SUMIFS(Extrato[Valor (R$)],Extrato[Categoria de Gasto],$A5,Extrato[Nome do Mês],B$1)*-1 -> 2847.98 | C5: =SUMIFS(Extrato[Valor (R$)],Extrato[Categoria de Gasto],$A5,Extrato[Nome do Mês],C$1)*-1 -> 2847.98 | D5: =SUMIFS(Extrato[Valor (R$)],Extrato[Categoria de Gasto],$A5,Extrato[Nome do Mês],D$1)*-1 -> 2847.98 | E5: =SUMIFS(Extrato[Valor (R$)],Extrato[Categoria de Gasto],$A5,Extrato[Nome do Mês],E$1)*-1 -> 2847.98 | F5: =SUMIFS(Extrato[Valor (R$)],Extrato[Categoria de Gasto],$A5,Extrato[Nome do Mês],F$1)*-1 -> 2847.98 | G5: =SUMIFS(Extrato[Valor (R$)],Extrato[Categoria de Gasto],$A5,Extrato[Nome do Mês],G$1)*-1 -> 2847.98 | H5: =SUMIFS(Extrato[Valor (R$)],Extrato[Categoria de Gasto],$A5,Extrato[Nome do Mês],H$1)*-1 -> 2847.98 | I5: =SUMIFS(Extrato[Valor (R$)],Extrato[Categoria de Gasto],$A5,Extrato[Nome do Mês],I$1)*-1 -> 0 | ... M5: =SUMIFS(Extrato[Valor (R$)],Extrato[Categoria de Gasto],$A5,Extrato[Nome do Mês],M$1)*-1 -> 0
A6: Recebimento | B6: =SUMIFS(Extrato[Valor (R$)],Extrato[Categoria de Gasto],$A6,Extrato[Nome do Mês],B$1) -> 20327.5 | C6: =SUMIFS(Extrato[Valor (R$)],Extrato[Categoria de Gasto],$A6,Extrato[Nome do Mês],C$1) -> 20671 | D6: =SUMIFS(Extrato[Valor (R$)],Extrato[Categoria de Gasto],$A6,Extrato[Nome do Mês],D$1) -> 20985 | E6: =SUMIFS(Extrato[Valor (R$)],Extrato[Categoria de Gasto],$A6,Extrato[Nome do Mês],E$1) -> 21150 | F6: =SUMIFS(Extrato[Valor (R$)],Extrato[Categoria de Gasto],$A6,Extrato[Nome do Mês],F$1) -> 21800 | G6: =SUMIFS(Extrato[Valor (R$)],Extrato[Categoria de Gasto],$A6,Extrato[Nome do Mês],G$1) -> 22100 | H6: =SUMIFS(Extrato[Valor (R$)],Extrato[Categoria de Gasto],$A6,Extrato[Nome do Mês],H$1) -> 22500 | I6: =SUMIFS(Extrato[Valor (R$)],Extrato[Categoria de Gasto],$A6,Extrato[Nome do Mês],I$1) -> 9800 | ... M6: =SUMIFS(Extrato[Valor (R$)],Extrato[Categoria de Gasto],$A6,Extrato[Nome do Mês],M$1) -> 0
A7: Recebimento Café | B7: =B6-B8 -> 16798.32 | C7: =C6-C8 -> 16868.32 | D7: =D6-D8 -> 16898.32 | E7: =E6-E8 -> 16598.32 | F7: =F6-F8 -> 16818.32 | G7: =G6-G8 -> 16918.32 | H7: =H6-H8 -> 17583.32 | I7: =I6-I8 -> 3300 | ... M7: =M6-M8 -> 0
A8: Recebimento Líquido | B8: =B6-SUM(B2,B4,B5) -> 3529.18 | C8: =C6-SUM(C2,C4,C5) -> 3802.68 | D8: =D6-SUM(D2,D4,D5) -> 4086.68 | E8: =E6-SUM(E2,E4,E5) -> 4551.68 | F8: =F6-SUM(F2,F4,F5) -> 4981.68 | G8: =G6-SUM(G2,G4,G5) -> 5181.68 | H8: =H6-SUM(H2,H4,H5) -> 4916.68 | I8: =I6-SUM(I2,I4,I5) -> 6500 | ... M8: =M6-SUM(M2,M4,M5) -> 0

Sheet Dados Financeiros
A1: Taxa Selic Anual | B1: 0.105
A2: Rentabilidade Anual Café | B2: =(Dashboard!AC4-Dashboard!AR4)/Dashboard!AC4 -> 0.20764752
A3: Rentabilidade Selic | B3: 0.0091
A4: Rentabilidade Café | B4: =(1 + B2)^(1/7) - 1 -> 0.027319997

Sheet Dashboard
N2: Lucro Líquido Médio (7meses) | AC2: Faturamento Médio (7 meses) | AR2: Despesa Média (7 meses)
N4: =AVERAGE('PF vs PJ'!B8:H8) -> 4435.7514 | AC4: =AVERAGE('PF vs PJ'!B6:H6) -> 21361.929 | AR4: =AVERAGE('PF vs PJ'!B7:H7) -> 16926.177
C11: Taxa Selic x Rendimento percentual | Y11: Lucro liquido mensal
C27: Receita x Despesa
AL34: 20000 | BD34: 10000
